a_beta_scalekit-4.0.2.dist-info/licenses/LICENSE
buf/__init__.py
buf/validate/__init__.py
buf/validate/expression_pb2.py
buf/validate/expression_pb2.pyi
buf/validate/expression_pb2_grpc.py
buf/validate/validate_pb2.py
buf/validate/validate_pb2.pyi
buf/validate/validate_pb2_grpc.py
buf/validate/priv/__init__.py
buf/validate/priv/private_pb2.py
buf/validate/priv/private_pb2.pyi
buf/validate/priv/private_pb2_grpc.py
scalekit/__init__.py
scalekit/client.py
scalekit/connected_accounts.py
scalekit/connection.py
scalekit/core.py
scalekit/directory.py
scalekit/domain.py
scalekit/m2m_client.py
scalekit/mcp.py
scalekit/organization.py
scalekit/passwordless.py
scalekit/role.py
scalekit/tools.py
scalekit/users.py
scalekit/common/__init__.py
scalekit/common/exceptions.py
scalekit/common/scalekit.py
scalekit/common/user.py
scalekit/connect/__init__.py
scalekit/connect/connect.py
scalekit/connect/modifier.py
scalekit/connect/types.py
scalekit/connect/frameworks/__init__.py
scalekit/connect/frameworks/langchain.py
scalekit/connect/models/__init__.py
scalekit/connect/models/tool_input_output.py
scalekit/connect/models/tool_mapping.py
scalekit/connect/models/requests/__init__.py
scalekit/connect/models/requests/create_connected_account_request.py
scalekit/connect/models/requests/mcp_request.py
scalekit/connect/models/requests/tool_request.py
scalekit/connect/models/responses/__init__.py
scalekit/connect/models/responses/create_connected_account_response.py
scalekit/connect/models/responses/create_mcp_response.py
scalekit/connect/models/responses/delete_connected_account_response.py
scalekit/connect/models/responses/execute_tool_response.py
scalekit/connect/models/responses/get_connected_account_auth_response.py
scalekit/connect/models/responses/get_mcp_response.py
scalekit/connect/models/responses/list_connected_accounts_response.py
scalekit/connect/models/responses/magic_link_response.py
scalekit/constants/__init__.py
scalekit/constants/user.py
scalekit/utils/__init__.py
scalekit/utils/directory.py
scalekit/v1/__init__.py
a_beta_scalekit-4.0.2.dist-info/METADATA
a_beta_scalekit-4.0.2.dist-info/WHEEL
a_beta_scalekit-4.0.2.dist-info/top_level.txt
a_beta_scalekit-4.0.2.dist-info/RECORD
